conport/__init__.py
conport/argument.py
conport/build.py
conport/cfg.ini
conport/config.py
conport/conport.py
conport/figure.py
conport/fixture.py
conport/mail.py
conport/report.py
conport/summary.py
conport/template.html
conport-1.1.8.data/data/cfg.ini
conport-1.1.8.data/data/template.html
conport-1.1.8.dist-info/METADATA
conport-1.1.8.dist-info/WHEEL
conport-1.1.8.dist-info/entry_points.txt
conport-1.1.8.dist-info/top_level.txt
conport-1.1.8.dist-info/RECORD
